{
  "info": {
    "id": "377061",
    "name": "Keventers Ice Cream",
    "cloudinaryImageId": "RX_THUMBNAIL/IMAGES/VENDOR/2024/5/6/eded9f86-f4ec-46cd-a7ea-49f078522101_377061.JPG",
    "locality": "Sarat Bose Road",
    "areaName": "Sarat Bose Road",
    "costForTwo": "₹200 for two",
    "cuisines": ["Ice Cream", "Desserts"],
    "avgRating": 4.6,
    "veg": true,
    "parentId": "272044",
    "avgRatingString": "4.6",
    "totalRatingsString": "1K+",
    "sla": {
      "deliveryTime": 34,
      "lastMileTravel": 8.7,
      "serviceability": "SERVICEABLE",
      "slaString": "30-35 mins",
      "lastMileTravelString": "8.7 km",
      "iconType": "ICON_TYPE_EMPTY"
    },
    "availability": {
      "nextCloseTime": "2024-07-30 05:00:00",
      "opened": true
    },
    "badges": {},
    "isOpen": true,
    "type": "F",
    "badgesV2": {
      "entityBadges": {
        "imageBased": {},
        "textBased": {},
        "textExtendedBadges": {}
      }
    },
    "aggregatedDiscountInfoV3": {
      "header": "50% OFF",
      "subHeader": "UPTO ₹100"
    },
    "differentiatedUi": {
      "displayType": "ADS_UI_DISPLAY_TYPE_ENUM_DEFAULT",
      "differentiatedUiMediaDetails": {
        "mediaType": "ADS_MEDIA_ENUM_IMAGE",
        "lottie": {},
        "video": {}
      }
    },
    "reviewsSummary": {},
    "displayType": "RESTAURANT_DISPLAY_TYPE_DEFAULT",
    "restaurantOfferPresentationInfo": {},
    "externalRatings": {
      "aggregatedRating": {
        "rating": "--"
      }
    },
    "ratingsDisplayPreference": "RATINGS_DISPLAY_PREFERENCE_SHOW_SWIGGY"
  },
  "analytics": {},
  "cta": {
    "link": "https://www.swiggy.com/restaurants/keventers-ice-cream-sarat-bose-road-kolkata-377061",
    "type": "WEBLINK"
  }
}
